omuserver/__init__.py
omuserver/__main__.py
omuserver/brand.py
omuserver/config.py
omuserver/consts.py
omuserver/dependency.py
omuserver/directories.py
omuserver/error.py
omuserver/frame.html
omuserver/helper.py
omuserver/index.html
omuserver/index_install.html
omuserver/security.py
omuserver/server.py
omuserver/session.py
omuserver/version.py
omuserver/api/__init__.py
omuserver/api/extension.py
omuserver/api/asset/__init__.py
omuserver/api/asset/extension.py
omuserver/api/asset/permissions.py
omuserver/api/dashboard/__init__.py
omuserver/api/dashboard/extension.py
omuserver/api/dashboard/permission.py
omuserver/api/endpoint/__init__.py
omuserver/api/endpoint/extension.py
omuserver/api/http/__init__.py
omuserver/api/http/extension.py
omuserver/api/http/permission.py
omuserver/api/i18n/__init__.py
omuserver/api/i18n/extension.py
omuserver/api/i18n/permissions.py
omuserver/api/logger/__init__.py
omuserver/api/logger/extension.py
omuserver/api/logger/permissions.py
omuserver/api/permission/__init__.py
omuserver/api/permission/extension.py
omuserver/api/plugin/__init__.py
omuserver/api/plugin/entry.py
omuserver/api/plugin/extension.py
omuserver/api/plugin/instance.py
omuserver/api/plugin/loader.py
omuserver/api/plugin/permissions.py
omuserver/api/plugin/session_connection.py
omuserver/api/plugin/transport.py
omuserver/api/registry/__init__.py
omuserver/api/registry/extension.py
omuserver/api/registry/registry.py
omuserver/api/server/__init__.py
omuserver/api/server/extension.py
omuserver/api/server/permissions.py
omuserver/api/session/__init__.py
omuserver/api/session/extension.py
omuserver/api/session/permissions.py
omuserver/api/signal/__init__.py
omuserver/api/signal/extension.py
omuserver/api/table/__init__.py
omuserver/api/table/cached_table.py
omuserver/api/table/extension.py
omuserver/api/table/serialized_table.py
omuserver/api/table/server_table.py
omuserver/api/table/session_table_handler.py
omuserver/api/table/adapters/__init__.py
omuserver-0.9.50.dist-info/METADATA
omuserver-0.9.50.dist-info/WHEEL
omuserver-0.9.50.dist-info/RECORD
