Metadata-Version: 2.4
Name: omuserver
Version: 0.9.50
Summary: Add your description here
Author-email: am230 <111672334+am230@users.noreply.github.com>
Requires-Python: >=3.12
Requires-Dist: aiohttp>=3.10.6
Requires-Dist: click>=8.1.7
Requires-Dist: cryptography>=45.0.7
Requires-Dist: loguru>=0.7.2
Requires-Dist: omu>=0.9.50
Requires-Dist: packaging>=24.1
Requires-Dist: pip>=24.2
Requires-Dist: psutil>=6.0.0
Requires-Dist: uv>=0.4.16
